docker_dynamic_inventory/__init__.py
docker_dynamic_inventory/cli.py
docker_dynamic_inventory/docker_dynamic_inventory.py
docker_dynamic_inventory-0.1.5.dist-info/DESCRIPTION.rst
docker_dynamic_inventory-0.1.5.dist-info/METADATA
docker_dynamic_inventory-0.1.5.dist-info/RECORD
docker_dynamic_inventory-0.1.5.dist-info/WHEEL
docker_dynamic_inventory-0.1.5.dist-info/entry_points.txt
docker_dynamic_inventory-0.1.5.dist-info/metadata.json
docker_dynamic_inventory-0.1.5.dist-info/top_level.txt
