Metadata-Version: 2.0
Name: docker-dynamic-inventory
Version: 0.1.5
Summary: Outputs a dynamic inventory of Docker containers for Ansible.
Home-page: https://github.com/inhumantsar/python-docker-dynamic-inventory
Author: Shaun Martin
Author-email: shaun@samsite.ca
License: BSD license
Keywords: docker-dynamic-inventory
Platform: UNKNOWN
Classifier: Development Status :: 2 - Pre-Alpha
Classifier: Intended Audience :: Developers
Classifier: License :: OSI Approved :: BSD License
Classifier: Natural Language :: English
Classifier: Programming Language :: Python :: 2
Classifier: Programming Language :: Python :: 2.7
Classifier: Programming Language :: Python :: 3
Classifier: Programming Language :: Python :: 3.4
Classifier: Programming Language :: Python :: 3.5
Classifier: Programming Language :: Python :: 3.6
Requires-Dist: docker (==3.1.0)
Requires-Dist: click (==6.7)
